{
    "overview": [],
    "ilo": [
        "Conduct research in biomedical and health sciences.",
        "Design experiments to research a current area of Biomedical science.",
        "Prepare and give oral and written presentation of the results.",
        "Express intellectual, scientific arguments; and",
        "Assimilate and critically evaluate existing knowledge within a scientific paradigm."
    ],
    "generic_skills": [
        "Articulating the breadth of knowledge gained in biomedical science;",
        "Critical appraisal of draft documents; developing the ability to exercise critical judgement;",
        "Expressing persuasive intellectual arguments;",
        "High level written report presentations;",
        "Managing a research project;",
        "Oral communication and presentation;",
        "Rigorous and independent thinking; and",
        "Time management and self-management skills"
    ],
    "elig_req": {
        "Prerequisites": [],
        "Corequisites": [],
        "Non-allowed subjects": [],
        "Inherent requirements (core participation requirements)": [
            {
                "type": "paragraph",
                "content": "Further details on how to seek academic adjustments can be found on the Student Equity and Disability Support website:http://services.unimelb.edu.au/student-equity/home"
            }
        ]
    },
    "assessment": [
        {
            "brief": "A literature review",
            "bullets": [
                "5000 words"
            ],
            "hurdle": "Must be completed to a satisfactory standard.",
            "timing": "Due towards the end of the first semester of project A",
            "percentage": "30%"
        },
        {
            "brief": "An oral presentation",
            "bullets": [
                "15 minutes"
            ],
            "hurdle": "Must be completed to a satisfactory standard.",
            "timing": "Due towards the end of the final semester of project A",
            "percentage": "20%"
        },
        {
            "brief": "A research report",
            "bullets": [
                "6000 words"
            ],
            "hurdle": "Must be completed to a satisfactory standard.",
            "timing": "Due towards the end of the final semester of project A",
            "percentage": "50%"
        },
        {
            "brief": null,
            "bullets": null,
            "hurdle": "Lab attendance, behaviour and performance assessed by supervisor near end of each semester of enrolment",
            "timing": "Throughout the teaching period",
            "percentage": "0%"
        }
    ],
    "date_times": [
        {
            "semester": "Semester 1 (Extended)",
            "principal_coordinator": null,
            "mode_of_delivery": "On Campus (Parkville)",
            "contact_hours": "",
            "total_time_commitment": "170 hours",
            "teaching_period": "26 February 2024 to 30 June 2024",
            "last_self_enrol_date": "8 March 2024",
            "census_date": "3 April 2024",
            "last_date_to_withdraw_without_fail": "3 May 2024",
            "assessment_period_ends": "30 June 2024",
            "contact_name": "Administrative Coordination",
            "contact_email": "Past students, future students, general enquiries"
        },
        {
            "semester": "Semester 2 (Extended)",
            "principal_coordinator": null,
            "mode_of_delivery": "On Campus (Parkville)",
            "contact_hours": "",
            "total_time_commitment": "170 hours",
            "teaching_period": "22 July 2024 to 20 December 2024",
            "last_self_enrol_date": "2 August 2024",
            "census_date": "2 September 2024",
            "last_date_to_withdraw_without_fail": "20 September 2024",
            "assessment_period_ends": "20 December 2024",
            "contact_name": "Administrative Coordination",
            "contact_email": "Past students, future students, general enquiries"
        }
    ]
}