{
    "overview": [
        "<p>Drama Therapy Methods 4 introduces students to psychodrama, playback theatre and therapeutic theatre performance, through experiential learning.</p>",
        "<p>In classroom practice students will experience a group drama therapy approach that integrates a range of methods and reflects on underlying core therapeutic processes.</p>",
        "<p>Students will further identify and demonstrate responsibilities of drama therapists in facilitating closings and endings.</p>"
    ],
    "ilo": [
        "appraise related drama therapy methods of psychodrama, playback or therapeutic theatre performance;",
        "facilitate group drama therapy experience that integrates a range of methods;",
        "identify and demonstrate responsibilities of drama therapists in facilitating closings and endings;",
        "expertly explain and critically reflect on a number of underlying core therapeutic processes."
    ],
    "generic_skills": [
        "communicate effectively in oral, written, digital and creative forms;",
        "apply critical thinking, analytical and problem-solving skills to unfamiliar challenges;",
        "promote and maintain the wellbeing of self and others;",
        "integrate personal reflection into the creative process."
    ],
    "elig_req": {
        "Prerequisites": [
            {
                "type": "table",
                "content": [
                    {
                        "Code": "CREA90015",
                        "Name": "Drama Therapy Methods 3",
                        "Teaching period": "Semester 1 (Early-Start) (On Campus - Southbank)",
                        "Credit Points": "12.5"
                    }
                ]
            }
        ],
        "Corequisites": [],
        "Non-allowed subjects": [
            {
                "type": "table",
                "content": [
                    {
                        "Code": "CREA90006",
                        "Name": "Dance Movement Therapy Methods 1",
                        "Teaching period": "Semester 1 (Early-Start) (On Campus - Southbank)",
                        "Credit Points": "12.5"
                    },
                    {
                        "Code": "CREA90011",
                        "Name": "Dance Movement Therapy Methods 2",
                        "Teaching period": "Semester 2 (Early-Start) (On Campus - Southbank)",
                        "Credit Points": "12.5"
                    },
                    {
                        "Code": "CREA90016",
                        "Name": "Dance Movement Therapy Methods 3",
                        "Teaching period": "Semester 1 (Early-Start) (On Campus - Southbank)",
                        "Credit Points": "12.5"
                    },
                    {
                        "Code": "CREA90021",
                        "Name": "Dance Movement Therapy Methods 4",
                        "Teaching period": "Semester 2 (Early-Start) (On Campus - Southbank)",
                        "Credit Points": "12.5"
                    }
                ]
            }
        ],
        "Inherent requirements (core participation requirements)": [
            {
                "type": "paragraph",
                "content": "Further details on how to seek academic adjustments can be found on the Student Equity and Disability Support website:http://services.unimelb.edu.au/student-equity/home"
            }
        ]
    },
    "assessment": [
        {
            "brief": "Essay - Drama therapy core processes at work in playback theatre",
            "bullets": [
                "1000 words"
            ],
            "hurdle": null,
            "timing": "First half of the teaching period",
            "percentage": "20%"
        },
        {
            "brief": "15-minute drama therapy performance exploring new self-awareness, and a 1000-word performance synopsis and process/reflection notes",
            "bullets": [
                "2500 words (equivalent)"
            ],
            "hurdle": null,
            "timing": "Second half of the teaching period",
            "percentage": "50%"
        },
        {
            "brief": "Essay - Theoretical underpinnings of one of: psychodrama, playback theatre or therapeutic theatre performance",
            "bullets": [
                "1500 words"
            ],
            "hurdle": null,
            "timing": "During the assessment period",
            "percentage": "30%"
        }
    ],
    "date_times": [
        {
            "semester": "Semester 2 (Early-Start)",
            "principal_coordinator": null,
            "mode_of_delivery": "On Campus (Southbank)",
            "contact_hours": "36 hours, comprising one 2.5-hour fortnightly class and three 7-hour on-campus intensive days",
            "total_time_commitment": "136 hours",
            "teaching_period": "15 July 2024 to 20 October 2024",
            "last_self_enrol_date": "26 July 2024",
            "census_date": "2 September 2024",
            "last_date_to_withdraw_without_fail": "20 September 2024",
            "assessment_period_ends": "15 November 2024",
            "contact_name": null,
            "contact_email": "drew.bird@unimelb.edu.au"
        }
    ]
}