{
    "overview": [
        "<p>The subject provides an introduction to understanding the relationship between music-making and social organisation in cross-cultural perspective.</p>",
        "<p>It presents case studies of traditional and contemporary music-making from different geographic areas, including Indigenous Australia, Africa, the Middle East, Asia, Europe, and the Americas.</p>"
    ],
    "ilo": [
        "an ability to understand music-making across diverse contexts;",
        "an informed understanding of the sociocultural contexts and the sound structures of different music cultures;",
        "a vocabulary for describing the fundamentals of music-making in general as well as their manifestations in specific cultural contexts;",
        "research skills to craft a semester-long study about music-making and;",
        "the ability to identify and evaluate major research trends in the discipline of ethnomusicology."
    ],
    "generic_skills": [
        "a capacity for independent critical thought about music from any time or place",
        "an openness to new ideas about what music is",
        "knowledge and skills which provide a basis for independent critical inquiry and research-based writing about music",
        "an informed understanding and appreciation of cultural diversity"
    ],
    "elig_req": {
        "Prerequisites": [],
        "Corequisites": [],
        "Non-allowed subjects": [],
        "Inherent requirements (core participation requirements)": [
            {
                "type": "paragraph",
                "content": "Further details on how to seek academic adjustments can be found on the Student Equity and Disability Support website:http://services.unimelb.edu.au/student-equity/home"
            }
        ]
    },
    "assessment": [
        {
            "brief": "A 1-hour listening exam held during the Week 12 lecture",
            "bullets": [
                "1200 words (equivalent)"
            ],
            "hurdle": null,
            "timing": "Week 12",
            "percentage": "30%"
        },
        {
            "brief": "An essay proposal and bibliography",
            "bullets": [
                "250 words"
            ],
            "hurdle": null,
            "timing": "Week 4",
            "percentage": "10%"
        },
        {
            "brief": "A literature review",
            "bullets": [
                "1250 words"
            ],
            "hurdle": null,
            "timing": "Week 8",
            "percentage": "20%"
        },
        {
            "brief": "An essay (excluding bibliography and discography)",
            "bullets": [
                "2000 words"
            ],
            "hurdle": null,
            "timing": "During the examination period",
            "percentage": "40%"
        }
    ],
    "date_times": [
        {
            "semester": "Semester 2",
            "principal_coordinator": null,
            "mode_of_delivery": "On Campus (Parkville)",
            "contact_hours": "36 hours, comprising one 1-hour lecture, one 1-hour seminar, and 1 hour engaging in online learning activities per week",
            "total_time_commitment": "156 hours",
            "teaching_period": "22 July 2024 to 20 October 2024",
            "last_self_enrol_date": "2 August 2024",
            "census_date": "2 September 2024",
            "last_date_to_withdraw_without_fail": "20 September 2024",
            "assessment_period_ends": "15 November 2024",
            "contact_name": null,
            "contact_email": "nicholas.tochka@unimelb.edu.au"
        }
    ]
}