[
    {
        "code": "GERM20002",
        "name": "German 8",
        "availability": "Offered Semester 2, 2024",
        "level": "Undergraduate Level 2",
        "credit": "12.5 credit points"
    },
    {
        "code": "GERM20003",
        "name": "German Cultural Studies B",
        "availability": "Offered Semester 1, 2024",
        "level": "Undergraduate Level 2",
        "credit": "12.5 credit points"
    },
    {
        "code": "GERM20004",
        "name": "German 3",
        "availability": "Offered Semester 1, 2024",
        "level": "Undergraduate Level 2",
        "credit": "12.5 credit points"
    },
    {
        "code": "GERM20005",
        "name": "German 4",
        "availability": "Offered Semester 2, 2024",
        "level": "Undergraduate Level 2",
        "credit": "12.5 credit points"
    },
    {
        "code": "GERM20006",
        "name": "German Cultural Studies A",
        "availability": "Offered Semester 2, 2024",
        "level": "Undergraduate Level 2",
        "credit": "12.5 credit points"
    },
    {
        "code": "GERM20007",
        "name": "German 5",
        "availability": "Offered Semester 1, 2024",
        "level": "Undergraduate Level 2",
        "credit": "12.5 credit points"
    },
    {
        "code": "GERM20008",
        "name": "German 6",
        "availability": "Offered Semester 2, 2024",
        "level": "Undergraduate Level 2",
        "credit": "12.5 credit points"
    },
    {
        "code": "GERM20009",
        "name": "German 9",
        "availability": "Offered Semester 1, 2024",
        "level": "Undergraduate Level 2",
        "credit": "12.5 credit points"
    },
    {
        "code": "GERM20010",
        "name": "German 10",
        "availability": "Offered Semester 2, 2024",
        "level": "Undergraduate Level 2",
        "credit": "12.5 credit points"
    },
    {
        "code": "GERM20011",
        "name": "Berlin and Beyond",
        "availability": "Offered Winter Term, 2024",
        "level": "Undergraduate Level 2",
        "credit": "12.5 credit points"
    },
    {
        "code": "GERM30001",
        "name": "German Cultural Studies B",
        "availability": "Offered Semester 1, 2024",
        "level": "Undergraduate Level 3",
        "credit": "12.5 credit points"
    },
    {
        "code": "GERM30002",
        "name": "German Cultural Studies C",
        "availability": "Offered Semester 1, 2024",
        "level": "Undergraduate Level 3",
        "credit": "12.5 credit points"
    },
    {
        "code": "GERM30003",
        "name": "German 9",
        "availability": "Offered Semester 1, 2024",
        "level": "Undergraduate Level 3",
        "credit": "12.5 credit points"
    },
    {
        "code": "GERM30004",
        "name": "German 10",
        "availability": "Offered Semester 2, 2024",
        "level": "Undergraduate Level 3",
        "credit": "12.5 credit points"
    },
    {
        "code": "GERM30005",
        "name": "German 5",
        "availability": "Offered Semester 1, 2024",
        "level": "Undergraduate Level 3",
        "credit": "12.5 credit points"
    },
    {
        "code": "GERM30006",
        "name": "German 6",
        "availability": "Offered Semester 2, 2024",
        "level": "Undergraduate Level 3",
        "credit": "12.5 credit points"
    },
    {
        "code": "GERM30021",
        "name": "German 7",
        "availability": "Offered Semester 1, 2024",
        "level": "Undergraduate Level 3",
        "credit": "12.5 credit points"
    },
    {
        "code": "GERM30022",
        "name": "German 8",
        "availability": "Offered Semester 2, 2024",
        "level": "Undergraduate Level 3",
        "credit": "12.5 credit points"
    },
    {
        "code": "GERM30024",
        "name": "Berlin and Beyond",
        "availability": "Offered Winter Term, 2024",
        "level": "Undergraduate Level 3",
        "credit": "12.5 credit points"
    },
    {
        "code": "GERM30025",
        "name": "Staging German",
        "availability": "Offered Semester 2, 2024",
        "level": "Undergraduate Level 3",
        "credit": "12.5 credit points"
    }
]